agentx/__init__.py
agentx/tools/StatisticalTools.py
agentx/tools/__init__.py
agentx/tools/date_tools.py
agentx/tools/rag_tools.py
agentx/tools/scraping_tools.py
agentx/tools/search_tools.py
agentx_tools-0.7.1.dist-info/LICENSE
agentx_tools-0.7.1.dist-info/METADATA
agentx_tools-0.7.1.dist-info/WHEEL
agentx_tools-0.7.1.dist-info/top_level.txt
agentx_tools-0.7.1.dist-info/RECORD
