Metadata-Version: 2.1
Name: agentx-tools
Version: 0.7.1
Summary: A collection of tools for Large Language Model Agents
Home-page: https://github.com/Tylerbryy/agentx
Author: Tyler Gibbs
Author-email: tylergibbs048@gmail.com
License: MIT
Classifier: Development Status :: 3 - Alpha
Classifier: License :: OSI Approved :: MIT License
Classifier: Programming Language :: Python :: 3
Classifier: Programming Language :: Python :: 3.6
Classifier: Programming Language :: Python :: 3.7
Classifier: Programming Language :: Python :: 3.8
Classifier: Programming Language :: Python :: 3.9
Classifier: Programming Language :: Python :: 3.10
License-File: LICENSE
Requires-Dist: numpy ==1.26.4
Requires-Dist: langchain-core <0.2.0,>=0.1.52
Requires-Dist: crewai-tools <=0.2.6,>=0.2.0
Requires-Dist: langchain-community <0.1.0,>=0.0.38
Requires-Dist: langchain <0.2.0,>=0.1.4
Requires-Dist: duckduckgo-search ==6.1.5
